cjm_fasthtml_file_browser/__init__.py
cjm_fasthtml_file_browser/_modidx.py
cjm_fasthtml_file_browser/components/__init__.py
cjm_fasthtml_file_browser/components/browser.py
cjm_fasthtml_file_browser/components/item.py
cjm_fasthtml_file_browser/components/listing.py
cjm_fasthtml_file_browser/components/path_bar.py
cjm_fasthtml_file_browser/components/toolbar.py
cjm_fasthtml_file_browser/core/__init__.py
cjm_fasthtml_file_browser/core/config.py
cjm_fasthtml_file_browser/core/html_ids.py
cjm_fasthtml_file_browser/core/models.py
cjm_fasthtml_file_browser/core/protocols.py
cjm_fasthtml_file_browser/providers/__init__.py
cjm_fasthtml_file_browser/providers/local.py
cjm_fasthtml_file_browser/routes/__init__.py
cjm_fasthtml_file_browser/routes/handlers.py
cjm_fasthtml_file_browser-0.0.4.dist-info/licenses/LICENSE
cjm_fasthtml_file_browser-0.0.4.dist-info/METADATA
cjm_fasthtml_file_browser-0.0.4.dist-info/WHEEL
cjm_fasthtml_file_browser-0.0.4.dist-info/entry_points.txt
cjm_fasthtml_file_browser-0.0.4.dist-info/top_level.txt
cjm_fasthtml_file_browser-0.0.4.dist-info/RECORD
