Metadata-Version: 2.4
Name: cjm-fasthtml-file-browser
Version: 0.0.4
Summary: Interactive file system navigation and selection UI components for FastHTML applications with extensible provider support.
Home-page: https://github.com/cj-mills/cjm-fasthtml-file-browser
Author: Christian J. Mills
Author-email: 9126128+cj-mills@users.noreply.github.com
License: Apache-2.0
Keywords: nbdev jupyter notebook python
Classifier: Development Status :: 4 - Beta
Classifier: Intended Audience :: Developers
Classifier: Natural Language :: English
Classifier: Programming Language :: Python :: 3.12
Classifier: Programming Language :: Python :: 3.13
Requires-Python: >=3.12
License-File: LICENSE
Requires-Dist: cjm_fasthtml_daisyui
Requires-Dist: cjm_fasthtml_lucide_icons
Requires-Dist: cjm_fasthtml_tailwind
Requires-Dist: cjm_file_discovery
Provides-Extra: dev
Dynamic: author
Dynamic: author-email
Dynamic: classifier
Dynamic: description
Dynamic: description-content-type
Dynamic: home-page
Dynamic: keywords
Dynamic: license
Dynamic: license-file
Dynamic: provides-extra
Dynamic: requires-dist
Dynamic: requires-python
Dynamic: summary
